Metadata-Version: 1.2
Name: kuenta-assistant
Version: 1.0.0
Summary: kuenta api assistant command line client
Home-page: https://git1-co.kuenta.net/yaien/kuenta-assistant
Author: Stevenson Marquez
Author-email: smarquez@kuenta.co
License: UNKNOWN
Download-URL: https://git1-co.kuenta.net/yaien/kuenta-assistant/-/archive/v1.0.0/kuenta-assistant-v1.0.0.tar.gz
Platform: UNKNOWN
Classifier: Programming Language :: Python :: 3
Classifier: License :: OSI Approved :: MIT License
Classifier: Operating System :: OS Independent
Requires-Python: >=3.6
